[
    {
        "id": "practical-registration-opens",
        "start": "2025-04-27T11:00:00-05:00",
        "end": "2025-04-27T12:45:00-05:00",
        "description": "Registration opens"
    },
    {
        "id": "practical-intro",
        "start": "2025-04-27T12:45:00-05:00",
        "end": "2025-04-27T13:00:00-05:00",
        "description": "Event intro"
    },
    {
        "id": "special-opening-keynote",
        "start": "2025-04-27T13:00:00-05:00",
        "end": "2025-04-27T13:45:00-05:00",
        "description": "Opening Keynote - \"Chasing Fun: Creating a Career You Love\"",
        "speakers": [{
            "name": "Michael Flarup",
            "image": "michael_flarup",
            "links": {
                "bluesky": "https://bsky.app/profile/flarup.bsky.social",
                "mastodon": "https://mastodon.social/@flarup",
                "twitter": "https://twitter.com/flarup"
            }
        }]
    },
    {
        "id": "session-tbd1",
        "start": "2025-04-27T14:00:00-05:00",
        "end": "2025-04-27T14:45:00-05:00",
        "description": "Josh Won’t Tell... Yet",
        "speakers": [],
        "emoji": "🤫"
    },
    {
        "id": "session-tbd2",
        "start": "2025-04-27T15:00:00-05:00",
        "end": "2025-04-27T15:30:00-05:00",
        "description": "Thin Crust is Optional",
        "speakers": [],
        "emoji": "🫥"
    },
    {
        "id": "break-sunday",
        "start": "2025-04-27T15:30:00-05:00",
        "end": "2025-04-27T16:00:00-05:00",
    },
    {
        "id": "session-tbd3",
        "start": "2025-04-27T16:00:00-05:00",
        "end": "2025-04-27T16:45:00-05:00",
        "description": "Awaiting Toppings...",
        "speakers": [],
        "emoji": "😶"
    },
    {
        "id": "session-allison-mcentire",
        "start": "2025-04-27T17:00:00-05:00",
        "end": "2025-04-27T17:45:00-05:00",
        "description": "Prompt Engineering for Accessibility",
        "speakers": [{
            "name": "Allison McEntire",
            "image": "allison_mcentire",
        }]
    },
    {
        "id": "breakfast-monday",
        "start": "2025-04-28T07:30:00-05:00",
        "end": "2025-04-28T08:55:00-05:00"
    },
    {
        "id": "practical-morning-welcome-monday",
        "start": "2025-04-28T08:55:00-05:00",
        "end": "2025-04-28T09:00:00-05:00",
        "description": "Morning welcome"
    },
    {
        "id": "session-antoine-van-der-lee",
        "start": "2025-04-28T09:05:00-05:00",
        "end": "2025-04-28T09:45:00-05:00",
        "description": "From Overwhelmed to Confident: Understanding Swift Concurrency",
        "speakers": [{
            "name": "Antoine van der Lee",
            "image": "antoine_van_der_lee",
            "links": {
                "bluesky": "https://bsky.app/profile/avanderlee.com",
                "mastodon": "https://mastodon.social/@swiftlee",
                "twitter": "https://twitter.com/twannl"
            }
        }]
    },
    {
        "id": "session-adrian-eves",
        "start": "2025-04-28T10:00:00-05:00",
        "end": "2025-04-28T10:45:00-05:00",
        "description": "I'm the Problem, It's Me",
        "speakers": [{
            "name": "Adrian Eves",
            "image": "adrian_eves",
            "links": {
                "bluesky": "https://bsky.app/profile/swifteves.bsky.social",
                "mastodon": "https://mastodon.social/@swifteves",
                "twitter": "https://twitter.com/swifteves"
            }
        }]
    },
    {
        "id": "session-tbd7",
        "start": "2025-04-28T11:00:00-05:00",
        "end": "2025-04-28T11:45:00-05:00",
        "description": "func reveal() -> Never",
        "speakers": [],
        "emoji": "🤯"
    },
    {
        "id": "lunch-monday",
        "start": "2025-04-28T11:45:00-05:00",
        "end": "2025-04-28T13:00:00-05:00"
    },
    {
        "id": "session-daniel-gauthier",
        "start": "2025-04-28T13:00:00-05:00",
        "end": "2025-04-28T13:45:00-05:00",
        "description": "Make Nice Things: An Engineer's “Made-Up Guide to App Design“",
        "speakers": [{
            "name": "Daniel Gauthier",
            "image": "daniel_gauthier",
            "links": {
                "bluesky": "https://bsky.app/profile/@danielmgauthier.bsky.social",
                "mastodon": "https://mastodon.social/@danielmgauthier",
                "twitter": "https://twitter.com/danielmgauthier"
            }
        }]
    },
    {
        "id": "session-danielle-lewis",
        "start": "2025-04-28T14:00:00-05:00",
        "end": "2025-04-28T14:45:00-05:00",
        "description": "Learning in Public: My Journey to 10",
        "speakers": [{
            "name": "Danielle Lewis",
            "image": "danielle_lewis",
            "links": {
                "bluesky": "https://bsky.app/profile/@daniellelewis.dev",
                "mastodon": "https://iosdev.space/@dlewisdev",
                "twitter": "https://twitter.com/dlewisdev"
            }
        }]
    },
    {
        "id": "session-tbd10",
        "start": "2025-04-28T15:00:00-05:00",
        "end": "2025-04-28T15:45:00-05:00",
        "description": "Session Hidden Behind a Paywall (Just Kidding)",
        "speakers": [],
        "emoji": "💰"
    },
    {
        "id": "session-hidde-van-der-ploeg",
        "start": "2025-04-28T15:45:00-05:00",
        "end": "2025-04-28T16:30:00-05:00",
        "description": "The Roast of your App's Design",
        "speakers": [{
            "name": "Hidde van der Ploeg",
            "image": "hidde_van_der_ploeg",
            "links": {
                "bluesky": "https://bsky.app/profile/did:plc:5zv4ptzbc44wjhrya2phyakd",
                "mastodon": "https://mastodon.design/@hidde",
                "twitter": "https://twitter.com/hiddevdploeg"
            }
        }]
    },
    {
        "id": "break-monday",
        "start": "2025-04-28T16:30:00-05:00",
        "end": "2025-04-28T17:00:00-05:00"
    },
    {
        "id": "special-launched-live",
        "start": "2025-04-28T17:00:00-05:00",
        "end": "2025-04-28T17:45:00-05:00",
        "description": "Launched Live with Charlie Chapman and guests",
        "speakers": [
            {
                "name": "Charlie Chapman",
                "image": "charlie_chapman",
                "links": {
                    "github": "https://github.com/charliemchapman",
                    "mastodon": "https://mastodon.social/@charliemchapman",
                    "threads": "https://www.threads.net/@charliemchapman",
                    "twitter": "https://twitter.com/_chuckyc",
                    "website": "https://charliemchapman.com"
                }
            },
            {
                "name": "Ryan Ashcraft",
                "image": "ryan_ashcraft",
                "links": {
                    "github": "https://github.com/ryanashcraft",
                    "mastodon": "https://mastodon.social/@ryanashcraft",
                    "bluesky": "https://bsky.app/profile/ryanashcraft.com",
                    "twitter": "https://twitter.com/ryanashcraft",
                    "website": "https://ryanashcraft.com"
                }
            },
            {
                "name": "Neem Serra",
                "image": "neem_serra",
                "links": {
                    "github": "https://github.com/teamneem",
                    "twitter": "https://twitter.com/TeamNeem",
                    "website": "https://neemserra.com/about/"
                }
            },
            {
                "name": "Edward Sánchez",
                "image": "edward_sanchez",
                "links": {
                    "twitter": "https://twitter.com/edwardsanchez",
                    "website": "https://edwardsanchez.design"
                }
            }
        ],
        "links": {
            "name": "Launched",
            "mastodon": "https://mastodon.social/@Launched",
            "twitter": "https://twitter.com/LaunchedFM",
            "website": "https://launchedfm.com/"
        }
    },
    {
        "id": "breakfast-tuesday",
        "start": "2025-04-29T07:30:00-05:00",
        "end": "2025-04-29T08:55:00-05:00",
    },
    {
        "id": "practical-morning-welcome-tuesday",
        "start": "2025-04-29T08:55:00-05:00",
        "end": "2025-04-29T09:00:00-05:00",
        "description": "Morning welcome"
    },
    {
        "id": "session-matthew-cassinelli",
        "start": "2025-04-29T09:00:00-05:00",
        "end": "2025-04-29T09:45:00-05:00",
        "description": "App Intents, Actions, and Personal Context - Oh My!",
        "speakers": [{
            "name": "Matthew Cassinelli",
            "image": "matthew_cassinelli",
            "links": {
                "bluesky": "https://bsky.app/profile/matthewcassinelli.bsky.social",
                "mastodon": "https://mastodon.social/@matthewcassinelli",
                "twitter": "https://twitter.com/matthewcassinelli"
            }
        }]
    },
    {
        "id": "session-matt-heaney",
        "start": "2025-04-29T10:00:00-05:00",
        "end": "2025-04-29T10:45:00-05:00",
        "description": "Serving Slices of Your App: The Underrated Potential of App Clips",
        "speakers": [{
            "name": "Matt Heaney",
            "image": "matt_heaney",
            "links": {
                "bluesky": "https://bsky.app/profile/mattheaney23.bsky.social",
                "mastodon": "https://mastodon.social/@MattHeaney23",
                "twitter": "https://twitter.com/MattHeaney23"
            }
        }]
    },
    {
        "id": "session-tbd14",
        "start": "2025-04-29T11:00:00-05:00",
        "end": "2025-04-29T11:45:00-05:00",
        "description": "This Talk is Private(set)",
        "speakers": [],
        "emoji": "🔒"
    },
    {
        "id": "lunch-tuesday",
        "start": "2025-04-29T11:45:00-05:00",
        "end": "2025-04-29T13:00:00-05:00",
        "description": "Lunch"
    },
    {
        "id": "session-tbd15",
        "start": "2025-04-29T13:00:00-05:00",
        "end": "2025-04-29T13:45:00-05:00",
        "description": "Even Spotlight Can’t Find This One Yet",
        "speakers": [],
        "emoji": "🔦"
    },
    {
        "id": "session-tbd16",
        "start": "2025-04-29T14:00:00-05:00",
        "end": "2025-04-29T14:45:00-05:00",
        "description": "Waiting for Josh Review",
        "speakers": [],
        "emoji": "👀"
    },
    {
        "id": "session-tbd17",
        "start": "2025-04-29T15:00:00-05:00",
        "end": "2025-04-29T15:45:00-05:00",
        "description": "One More Topping… I Mean, Thing",
        "speakers": [],
        "emoji": "🙈"
    },
    {
        "id": "special-concert",
        "start": "2025-04-29T16:00:00-05:00",
        "end": "2025-04-29T16:45:00-05:00",
        "description": "Musical performance by James Dempsey and the Breakpoints",
        "links": {
            "name": "James Dempsey and the Breakpoints",
            "website": "https://jamesdempsey.net/music"
        }
    },
    {
        "id": "special-closing-keynote",
        "start": "2025-04-29T17:00:00-05:00",
        "end": "2025-04-29T17:45:00-05:00",
        "description": "Closing Keynote",
        "speakers": [],
        "emoji": "🏁"
    },
    {
        "id": "practical-closing-words",
        "start": "2025-04-29T17:45:00-05:00",
        "end": "2025-04-29T18:00:00-05:00",
        "description": "Closing Words"
    }
]
